{"_type":"export","__export_format":4,"__export_date":"2023-09-04T20:37:11.266Z","__export_source":"insomnia.desktop.app:v2023.5.7","resources":[{"_id":"req_e64294e3fef74ace8472f7344939bb29","parentId":"wrk_6aa6231411e54e0c8e78ec9fca9f6c61","modified":1693859765694,"created":1693855116066,"url":"{{ _.BASE_URL }}/api/cupcakes","name":"Create a Cupcake","description":"","method":"POST","body":{"mimeType":"application/json","text":"{\n\t\"flavor\": \"Banana Chocolate\",\n\t\"size\": \"Standard\",\n\t\"rating\": 10000,\n\t\"image_url\": \"https://grandbaby-cakes.com/wp-content/uploads/2019/07/Strawberry-cupcakes-04.jpg\"\n}"},"parameters":[],"headers":[{"name":"Content-Type","value":"application/json"},{"name":"User-Agent","value":"Insomnia/2023.5.7","id":"pair_b7c88b670a174939a52c806f5af026ee"}],"authentication":{},"metaSortKey":-1693855116066,"isPrivate":false,"settingStoreCookies":true,"settingSendCookies":true,"settingDisableRenderRequestBody":false,"settingEncodeUrl":true,"settingRebuildPath":true,"settingFollowRedirects":"global","_type":"request"},{"_id":"wrk_6aa6231411e54e0c8e78ec9fca9f6c61","parentId":null,"modified":1693854544362,"created":1693854544362,"name":"Get All Cupcakes","description":"","scope":"collection","_type":"workspace"},{"_id":"req_03c27d85ccd54a968b178a87cfa05924","parentId":"wrk_6aa6231411e54e0c8e78ec9fca9f6c61","modified":1693859751737,"created":1693854788386,"url":"http://localhost:5001/api/cupcakes/30000","name":"Get Cupcake By ID","description":"","method":"GET","body":{},"parameters":[],"headers":[{"name":"User-Agent","value":"Insomnia/2023.5.7"}],"authentication":{},"metaSortKey":-1693854788386,"isPrivate":false,"settingStoreCookies":true,"settingSendCookies":true,"settingDisableRenderRequestBody":false,"settingEncodeUrl":true,"settingRebuildPath":true,"settingFollowRedirects":"global","_type":"request"},{"_id":"req_ec3a0cb9635d49ff8892754ae617022f","parentId":"wrk_6aa6231411e54e0c8e78ec9fca9f6c61","modified":1693859725890,"created":1693854548025,"url":"{{ _.BASE_URL }}/api/cupcakes","name":"Get all Cupcakes","description":"","method":"GET","body":{},"parameters":[],"headers":[{"name":"User-Agent","value":"Insomnia/2023.5.7"}],"authentication":{},"metaSortKey":-1693854548025,"isPrivate":false,"settingStoreCookies":true,"settingSendCookies":true,"settingDisableRenderRequestBody":false,"settingEncodeUrl":true,"settingRebuildPath":true,"settingFollowRedirects":"global","_type":"request"},{"_id":"env_042e664914c109c9764ac99dcce778e3c282e8fa","parentId":"wrk_6aa6231411e54e0c8e78ec9fca9f6c61","modified":1693859696385,"created":1693854544366,"name":"Base Environment","data":{"BASE_URL":"http://localhost:5001"},"dataPropertyOrder":{"&":["BASE_URL"]},"color":null,"isPrivate":false,"metaSortKey":1693854544366,"_type":"environment"},{"_id":"jar_042e664914c109c9764ac99dcce778e3c282e8fa","parentId":"wrk_6aa6231411e54e0c8e78ec9fca9f6c61","modified":1693854544367,"created":1693854544367,"name":"Default Jar","cookies":[],"_type":"cookie_jar"}]}